rummy_circ_otp.py
rummy_circ_otp-1.0.dist-info/METADATA
rummy_circ_otp-1.0.dist-info/WHEEL
rummy_circ_otp-1.0.dist-info/top_level.txt
rummy_circ_otp-1.0.dist-info/RECORD
