Metadata-Version: 2.1
Name: rummy-circ-otp
Version: 1.0
Requires-Dist: requests
